HACKING
LICENSE
MANIFEST.in
README
runtests
setup.py
tox.ini
django_factory/__init__.py
django_factory/factory.py
django_factory/generators.py
django_factory/models.py
django_factory/testcase.py
django_factory.egg-info/PKG-INFO
django_factory.egg-info/SOURCES.txt
django_factory.egg-info/dependency_links.txt
django_factory.egg-info/requires.txt
django_factory.egg-info/top_level.txt
django_project/__init__.py
django_project/manage.py
django_project/settings.py
django_project/urls.py
django_project/factory_tests/__init__.py
django_project/factory_tests/models.py
django_project/factory_tests/tests.py
django_project/factory_tests/views.py