Metadata-Version: 1.0
Name: django-factory
Version: 0.10
Summary: Generic factory for creating instances of Django models in tests.
Home-page: https://launchpad.net/django_factory
Author: James Westby
Author-email: james.westby@canonical.com
License: Apache-2
Platform: UNKNOWN
Classifier: Development Status :: 4 - Beta
Classifier: Framework :: Django
Classifier: Intended Audience :: Developers
Classifier: License :: OSI Approved :: Apache Software License
Classifier: Programming Language :: Python :: 2.6
Classifier: Topic :: Database
Classifier: Topic :: Software Development :: Libraries :: Python Modules
Classifier: Topic :: Software Development :: Testing
